README.rst
setup.py
bwhu/__init__.py
bwhu/hu.py
bwhu.egg-info/PKG-INFO
bwhu.egg-info/SOURCES.txt
bwhu.egg-info/dependency_links.txt
bwhu.egg-info/top_level.txt