Metadata-Version: 2.1
Name: bwhu
Version: 1.0.0
Summary: this is a test lib created by QJ
Home-page: https://github.com/QianjiangHu/bwhu
Author: QJ
Author-email: qianjianghu@gmail.com
